ubs_transactions_csv_parser/AccountExportData.py
ubs_transactions_csv_parser/AccountTransaction.py
ubs_transactions_csv_parser/CardExportData.py
ubs_transactions_csv_parser/CardTransaction.py
ubs_transactions_csv_parser/__init__.py
ubs_transactions_csv_parser/currency.py
ubs_transactions_csv_parser-0.2.0.dist-info/licenses/LICENSE
ubs_transactions_csv_parser-0.2.0.dist-info/METADATA
ubs_transactions_csv_parser-0.2.0.dist-info/WHEEL
ubs_transactions_csv_parser-0.2.0.dist-info/top_level.txt
ubs_transactions_csv_parser-0.2.0.dist-info/RECORD
