Metadata-Version: 2.4
Name: ubs-transactions-csv-parser
Version: 0.2.0
Summary: Parse and deduplicate UBS transaction CSV files.
Home-page: https://github.com/rktr1998/ubs-transactions-csv-parser
Author: Riccardo Torreggiani
Author-email: Riccardo Torreggiani <riccardo.torreggiani@gmail.com>
License: MIT License
Project-URL: Homepage, https://github.com/rktr1998/ubs-transactions-csv-parser
Classifier: Programming Language :: Python :: 3
Classifier: License :: OSI Approved :: MIT License
Classifier: Operating System :: OS Independent
Requires-Python: >=3.11
License-File: LICENSE
Requires-Dist: pycountry>=23
Dynamic: license-file
